<?xml version="1.0" encoding="UTF-8"?>
<compositeCheatsheet name="Unit 1">
   <taskGroup kind="sequence" name="Getting Set Up" skip="false">
      <intro>
         <b>Introduction</b>
      </intro>
      <onCompletion>
         <b>Conclusion</b>
      </onCompletion>
      <task kind="cheatsheet" name="Switch to jACT-R Perspective" skip="true">
         <intro>
            First, let&apos;s make sure you&apos;re using the jACT-R perspective.
         </intro>
         <onCompletion>
            With the perspective set, we can import the unit 1 tutorial.
         </onCompletion>
         <param name="path" value="../../basics/perspectives.xml">
         </param>
      </task>
      <task kind="cheatsheet" name="Import unit1" skip="false">
         <intro>
            Now let&apos;s snag unit 1 and open up the docs.
         </intro>
         <param name="path" value="import.xml">
         </param>
      </task>
      <task kind="cheatsheet" name="Open count model" skip="false">
         <intro>
            Let&apos;s open up the count model so you know what everything looks like.
         </intro>
         <onCompletion>
            In the middle of the screen you have your model. To the right is a structured outline of the model which is useful for navigation. To the left is the explorer.
         </onCompletion>
         <param name="path" value="open.xml">
         </param>
      </task>
      <task kind="cheatsheet" name="Run, baby, run" skip="false">
         <onCompletion>
            The rest of the tutorial goes through the other models in the unit. Follow along, and happy hacking.
         </onCompletion>
         <param name="path" value="run.xml">
         </param>
      </task>
   </taskGroup>
</compositeCheatsheet>
